context_aware/mcp_server.py
context_aware/analyzer/__init__.py
context_aware/analyzer/base_analyzer.py
context_aware/analyzer/ts_analyzer.py
context_aware/cli/__init__.py
context_aware/cli/main.py
context_aware/compiler/__init__.py
context_aware/compiler/simple_compiler.py
context_aware/integrations/__init__.py
context_aware/integrations/claude.py
context_aware/linker/__init__.py
context_aware/linker/graph_linker.py
context_aware/models/__init__.py
context_aware/models/context_item.py
context_aware/router/__init__.py
context_aware/router/graph_router.py
context_aware/services/embedding_service.py
context_aware/store/__init__.py
context_aware/store/sqlite_store.py
context_aware/tools/__init__.py
context_aware/tools/structure.py
context_aware-0.3.0.dist-info/licenses/LICENSE
context_aware-0.3.0.dist-info/METADATA
context_aware-0.3.0.dist-info/WHEEL
context_aware-0.3.0.dist-info/entry_points.txt
context_aware-0.3.0.dist-info/top_level.txt
context_aware-0.3.0.dist-info/RECORD
