Metadata-Version: 2.4
Name: context-aware
Version: 0.3.0
Summary: A lightweight, agent-centric context management framework for LLMs.
Author: Ferdinando Bonsegna
Project-URL: Homepage, https://github.com/FerdinandoBonsegna/ContextAware
Project-URL: Bug Tracker, https://github.com/FerdinandoBonsegna/ContextAware/issues
Classifier: Programming Language :: Python :: 3
Classifier: License :: OSI Approved :: MIT License
Classifier: Operating System :: OS Independent
Classifier: Topic :: Software Development :: Libraries :: Python Modules
Classifier: Intended Audience :: Developers
Requires-Python: >=3.8
License-File: LICENSE
Requires-Dist: pydantic>=2.0.0
Requires-Dist: tqdm>=4.0.0
Requires-Dist: mcp>=1.0.0
Requires-Dist: tree-sitter<0.21.0,>=0.20.0
Requires-Dist: tree-sitter-languages>=1.0.0
Provides-Extra: semantic
Requires-Dist: numpy>=1.24.0; extra == "semantic"
Requires-Dist: sentence-transformers>=2.2.0; extra == "semantic"
Provides-Extra: all
Requires-Dist: numpy>=1.24.0; extra == "all"
Requires-Dist: sentence-transformers>=2.2.0; extra == "all"
Dynamic: license-file
